placeholder/__init__.py
placeholder/creator.py
placeholder/public/NotoSansKR-Regular.ttf
placeholder_img-0.5.dist-info/METADATA
placeholder_img-0.5.dist-info/WHEEL
placeholder_img-0.5.dist-info/top_level.txt
placeholder_img-0.5.dist-info/RECORD
